plane_py/__init__.py
plane_py/_http_client.py
plane_py/_types.py
plane_py/_utils.py
plane_py/api.py
plane_py/errors.py
plane_py/endpoints/base.py
plane_py/endpoints/cycle.py
plane_py/endpoints/cycleissue.py
plane_py/endpoints/intakeissue.py
plane_py/endpoints/issue.py
plane_py/endpoints/issueactivity.py
plane_py/endpoints/issuecomment.py
plane_py/endpoints/issueproperty.py
plane_py/endpoints/issuetype.py
plane_py/endpoints/label.py
plane_py/endpoints/link.py
plane_py/endpoints/module.py
plane_py/endpoints/moduleissue.py
plane_py/endpoints/project.py
plane_py/endpoints/propertyoption.py
plane_py/endpoints/propertyvalue.py
plane_py/endpoints/state.py
plane_py-1.1.0.dist-info/METADATA
plane_py-1.1.0.dist-info/WHEEL
plane_py-1.1.0.dist-info/licenses/LICENSE
plane_py-1.1.0.dist-info/RECORD
